stray/__init__.py
stray/camera.py
stray/debugger.py
stray/detection.py
stray/export.py
stray/linalg.py
stray/primitives.py
stray/renderer.py
stray/scene.py
stray/segmentation.py
stray/scripts/__init__.py
stray/scripts/bake.py
stray/scripts/cut.py
stray/scripts/dataset_export.py
stray/scripts/dataset_import.py
stray/scripts/debug_frames.py
stray/scripts/scale_calibration.py
stray/scripts/show.py
stray/training/__init__.py
stray/training/data.py
stray/training/loss.py
stray/training/model.py
stray/training/util.py
stray/utils/__init__.py
stray/utils/detectron2.py
stray-0.0.9.dist-info/LICENSE
stray-0.0.9.dist-info/METADATA
stray-0.0.9.dist-info/WHEEL
stray-0.0.9.dist-info/entry_points.txt
stray-0.0.9.dist-info/top_level.txt
stray-0.0.9.dist-info/RECORD
