Metadata-Version: 2.1
Name: stray
Version: 0.0.9
Summary: Stray SDK
Home-page: https://github.com/StrayRobots/stray
Author: Stray Robots
Author-email: hello@strayrobots.io
License: UNKNOWN
Project-URL: Bug Tracker, https://github.com/StrayRobots/stray/issues
Platform: UNKNOWN
Classifier: Programming Language :: Python :: 3
Classifier: License :: OSI Approved :: MIT License
Classifier: Operating System :: OS Independent
Requires-Python: >=3.8
License-File: LICENSE
Requires-Dist: torch
Requires-Dist: numpy
Requires-Dist: trimesh
Requires-Dist: scipy
Requires-Dist: pillow
Requires-Dist: scikit-video
Requires-Dist: scikit-spatial
Requires-Dist: pycocotools
Requires-Dist: open3d
Requires-Dist: opencv-python
Requires-Dist: pytorch-lightning
Requires-Dist: click
Requires-Dist: tqdm
